dshelper/__init__.py
dshelper/correlation.py
dshelper/evaluation.py
dshelper/missing.py
dshelper/preprocessing.py
dshelper_ayushlokre-0.1.0.dist-info/licenses/LICENSE
dshelper_ayushlokre-0.1.0.dist-info/METADATA
dshelper_ayushlokre-0.1.0.dist-info/WHEEL
dshelper_ayushlokre-0.1.0.dist-info/top_level.txt
dshelper_ayushlokre-0.1.0.dist-info/RECORD
